get_pdf_from_docx/__init__.py
get_pdf_from_docx/helpers/__init__.py
get_pdf_from_docx/helpers/wordtools.py
get_pdf_from_docx/main.py
get_pdf_from_docx-0.2.1.dist-info/entry_points.txt
get_pdf_from_docx-0.2.1.dist-info/METADATA
get_pdf_from_docx-0.2.1.dist-info/WHEEL
get_pdf_from_docx-0.2.1.dist-info/RECORD
